xftpd/__init__.py
xftpd/ftp_server/__init__.py
xftpd/ftps_server/__init__.py
xftpd/sftp_server/__init__.py
xftpd/tftp_server/__init__.py
xftpd-0.1.0.dist-info/LICENSE
xftpd-0.1.0.dist-info/METADATA
xftpd-0.1.0.dist-info/WHEEL
xftpd-0.1.0.dist-info/top_level.txt
xftpd-0.1.0.dist-info/RECORD
