Metadata-Version: 2.1
Name: xftpd
Version: 0.1.0
Summary: XFTPD Server: SFTP and FTP server Class that can be started and stopped programmatically.
Home-page: https://github.com/mapp-john/xftpd
Author: John Mapp
Author-email: spidermonkey2012@gmail.com
License: UNKNOWN
Platform: UNKNOWN
Classifier: Programming Language :: Python :: 3
Classifier: License :: OSI Approved :: MIT License
Classifier: Operating System :: OS Independent
Requires-Python: >=3.6
Requires-Dist: netifaces
Requires-Dist: sftpserver
Requires-Dist: pyftpdlib
Requires-Dist: paramiko
Requires-Dist: cryptography
